pyluos/__init__.py
pyluos/device.py
pyluos/utils.py
pyluos/version.py
pyluos/integration/__init__.py
pyluos/integration/freedomRobotics.py
pyluos/io/__init__.py
pyluos/io/serial_io.py
pyluos/io/ws.py
pyluos/services/__init__.py
pyluos/services/angle.py
pyluos/services/color.py
pyluos/services/distance.py
pyluos/services/gate.py
pyluos/services/imu.py
pyluos/services/light.py
pyluos/services/load.py
pyluos/services/motor.py
pyluos/services/pipe.py
pyluos/services/pressure.py
pyluos/services/service.py
pyluos/services/servoMotor.py
pyluos/services/state.py
pyluos/services/unknown.py
pyluos/services/void.py
pyluos/services/voltage.py
pyluos/tools/__init__.py
pyluos/tools/bootloader.py
pyluos/tools/discover.py
pyluos/tools/shell.py
pyluos/tools/usb2ws.py
pyluos/tools/usb_gate.py
pyluos/tools/wifi_gate.py
pyluos-3.0.0.dist-info/LICENSE
pyluos-3.0.0.dist-info/METADATA
pyluos-3.0.0.dist-info/WHEEL
pyluos-3.0.0.dist-info/entry_points.txt
pyluos-3.0.0.dist-info/top_level.txt
pyluos-3.0.0.dist-info/RECORD
