Metadata-Version: 2.1
Name: pyluos
Version: 3.0.0
Summary: Python library to set the high level behavior of your device based on Luos embedded system.
Home-page: https://docs.luos.io/pages/high/pyluos.html
Author: Luos
Author-email: hello@luos.io
License: MIT
License-File: LICENSE
Requires-Dist: future
Requires-Dist: websocket-client
Requires-Dist: pyserial >3
Requires-Dist: SimpleWebSocketServer
Requires-Dist: zeroconf
Requires-Dist: numpy
Requires-Dist: anytree
Requires-Dist: crc8
Requires-Dist: ipython
Requires-Dist: requests
Provides-Extra: jupyter-integration
Requires-Dist: ipywidgets ; extra == 'jupyter-integration'
Provides-Extra: tests
Requires-Dist: pytest ; extra == 'tests'
Requires-Dist: flake8 ; extra == 'tests'
